{
  "createdAt": "2026-03-06T08:58:13.859Z",
  "expiresAt": "2026-03-06T09:58:13.859Z",
  "key": "{\"resource\":\"odpt:BusstopPoleTimetable\",\"query\":\"odpt:operator=odpt.Operator:TokyuBus&odpt:busstopPole=odpt.BusstopPole:TokyuBus.Nagasaka.00240741.b\",\"dump\":false}",
  "payload": {
    "meta": {
      "url": "https://api.odpt.org/api/v4/odpt:BusstopPoleTimetable?odpt:operator=odpt.Operator:TokyuBus&odpt:busstopPole=odpt.BusstopPole:TokyuBus.Nagasaka.00240741.b&acl:consumerKey=841qfdgzgywu5oktxrzqst5mosl5apeis3r5bz98aorxk8175pr1e7zd2k4pywqh",
      "count": 3,
      "maybeTruncated": false,
      "dump": false,
      "cacheHit": false,
      "cacheKey": "{\"resource\":\"odpt:BusstopPoleTimetable\",\"query\":\"odpt:operator=odpt.Operator:TokyuBus&odpt:busstopPole=odpt.BusstopPole:TokyuBus.Nagasaka.00240741.b\",\"dump\":false}"
    },
    "data": [
      {
        "@id": "urn:ucode:_00001C00000000000001000003877FFF",
        "@type": "odpt:BusstopPoleTimetable",
        "dc:date": "2026-02-02T15:35:32+09:00",
        "@context": "http://vocab.odpt.org/context_odpt_BusstopPoleTimetable.jsonld",
        "dc:title": "宮０６.\n\t\t\t\t\t\t\t\t\t\t\n\t\t\t\t\t\t\t\t\t\t\n\t\t\t\t\t\t\t\t\t\t＜宮前区役所前経由＞ 宮前平駅ゆき\n\t\t\t\t\t\t\t\t\t\t宮前区役所前経由 宮前平駅ゆき\n\t\t\t\t\t\t\t\t\t:長坂:平日",
        "odpt:note": "お問合せ先:東急バス 高津営業所",
        "owl:sameAs": "odpt.BusstopPoleTimetable:TokyuBus.Miya06.Nagasaka.00240741.b.0004602726.4.Weekday",
        "odpt:busroute": [
          "odpt.Busroute:TokyuBus.Miya06"
        ],
        "odpt:calendar": "odpt.Calendar:Weekday",
        "odpt:operator": "odpt.Operator:TokyuBus",
        "odpt:busstopPole": "odpt.BusstopPole:TokyuBus.Nagasaka.00240741.b",
        "odpt:busDirection": [
          "odpt.BusDirection:TokyuBus.Miyamaedairaeki"
        ],
        "odpt:busstopPoleTimetableObject": [
          {
            "odpt:isMidnight": false,
            "odpt:departureTime": "06:47",
            "odpt:busroutePattern": "odpt.BusroutePattern:TokyuBus.Miya06.0004602726",
            "odpt:destinationBusstopPole": "odpt.BusstopPole:TokyuBus.Miyamaedairaeki.00240726."
          },
          {
            "odpt:isMidnight": false,
            "odpt:departureTime": "07:12",
            "odpt:busroutePattern": "odpt.BusroutePattern:TokyuBus.Miya06.0004602726",
            "odpt:destinationBusstopPole": "odpt.BusstopPole:TokyuBus.Miyamaedairaeki.00240726."
          },
          {
            "odpt:isMidnight": false,
            "odpt:departureTime": "07:37",
            "odpt:busroutePattern": "odpt.BusroutePattern:TokyuBus.Miya06.0004602726",
            "odpt:destinationBusstopPole": "odpt.BusstopPole:TokyuBus.Miyamaedairaeki.00240726."
          },
          {
            "odpt:isMidnight": false,
            "odpt:departureTime": "08:02",
            "odpt:busroutePattern": "odpt.BusroutePattern:TokyuBus.Miya06.0004602726",
            "odpt:destinationBusstopPole": "odpt.BusstopPole:TokyuBus.Miyamaedairaeki.00240726."
          },
          {
            "odpt:isMidnight": false,
            "odpt:departureTime": "08:27",
            "odpt:busroutePattern": "odpt.BusroutePattern:TokyuBus.Miya06.0004602726",
            "odpt:destinationBusstopPole": "odpt.BusstopPole:TokyuBus.Miyamaedairaeki.00240726."
          },
          {
            "odpt:isMidnight": false,
            "odpt:departureTime": "08:52",
            "odpt:busroutePattern": "odpt.BusroutePattern:TokyuBus.Miya06.0004602726",
            "odpt:destinationBusstopPole": "odpt.BusstopPole:TokyuBus.Miyamaedairaeki.00240726."
          },
          {
            "odpt:isMidnight": false,
            "odpt:departureTime": "09:19",
            "odpt:busroutePattern": "odpt.BusroutePattern:TokyuBus.Miya06.0004602726",
            "odpt:destinationBusstopPole": "odpt.BusstopPole:TokyuBus.Miyamaedairaeki.00240726."
          },
          {
            "odpt:isMidnight": false,
            "odpt:departureTime": "10:09",
            "odpt:busroutePattern": "odpt.BusroutePattern:TokyuBus.Miya06.0004602726",
            "odpt:destinationBusstopPole": "odpt.BusstopPole:TokyuBus.Miyamaedairaeki.00240726."
          },
          {
            "odpt:isMidnight": false,
            "odpt:departureTime": "10:59",
            "odpt:busroutePattern": "odpt.BusroutePattern:TokyuBus.Miya06.0004602726",
            "odpt:destinationBusstopPole": "odpt.BusstopPole:TokyuBus.Miyamaedairaeki.00240726."
          },
          {
            "odpt:isMidnight": false,
            "odpt:departureTime": "11:49",
            "odpt:busroutePattern": "odpt.BusroutePattern:TokyuBus.Miya06.0004602726",
            "odpt:destinationBusstopPole": "odpt.BusstopPole:TokyuBus.Miyamaedairaeki.00240726."
          },
          {
            "odpt:isMidnight": false,
            "odpt:departureTime": "12:39",
            "odpt:busroutePattern": "odpt.BusroutePattern:TokyuBus.Miya06.0004602726",
            "odpt:destinationBusstopPole": "odpt.BusstopPole:TokyuBus.Miyamaedairaeki.00240726."
          },
          {
            "odpt:isMidnight": false,
            "odpt:departureTime": "13:29",
            "odpt:busroutePattern": "odpt.BusroutePattern:TokyuBus.Miya06.0004602726",
            "odpt:destinationBusstopPole": "odpt.BusstopPole:TokyuBus.Miyamaedairaeki.00240726."
          },
          {
            "odpt:isMidnight": false,
            "odpt:departureTime": "14:19",
            "odpt:busroutePattern": "odpt.BusroutePattern:TokyuBus.Miya06.0004602726",
            "odpt:destinationBusstopPole": "odpt.BusstopPole:TokyuBus.Miyamaedairaeki.00240726."
          },
          {
            "odpt:isMidnight": false,
            "odpt:departureTime": "15:09",
            "odpt:busroutePattern": "odpt.BusroutePattern:TokyuBus.Miya06.0004602726",
            "odpt:destinationBusstopPole": "odpt.BusstopPole:TokyuBus.Miyamaedairaeki.00240726."
          },
          {
            "odpt:isMidnight": false,
            "odpt:departureTime": "15:59",
            "odpt:busroutePattern": "odpt.BusroutePattern:TokyuBus.Miya06.0004602726",
            "odpt:destinationBusstopPole": "odpt.BusstopPole:TokyuBus.Miyamaedairaeki.00240726."
          },
          {
            "odpt:isMidnight": false,
            "odpt:departureTime": "16:49",
            "odpt:busroutePattern": "odpt.BusroutePattern:TokyuBus.Miya06.0004602726",
            "odpt:destinationBusstopPole": "odpt.BusstopPole:TokyuBus.Miyamaedairaeki.00240726."
          },
          {
            "odpt:isMidnight": false,
            "odpt:departureTime": "17:39",
            "odpt:busroutePattern": "odpt.BusroutePattern:TokyuBus.Miya06.0004602726",
            "odpt:destinationBusstopPole": "odpt.BusstopPole:TokyuBus.Miyamaedairaeki.00240726."
          },
          {
            "odpt:isMidnight": false,
            "odpt:departureTime": "18:29",
            "odpt:busroutePattern": "odpt.BusroutePattern:TokyuBus.Miya06.0004602726",
            "odpt:destinationBusstopPole": "odpt.BusstopPole:TokyuBus.Miyamaedairaeki.00240726."
          },
          {
            "odpt:isMidnight": false,
            "odpt:departureTime": "19:19",
            "odpt:busroutePattern": "odpt.BusroutePattern:TokyuBus.Miya06.0004602726",
            "odpt:destinationBusstopPole": "odpt.BusstopPole:TokyuBus.Miyamaedairaeki.00240726."
          },
          {
            "odpt:isMidnight": false,
            "odpt:departureTime": "20:09",
            "odpt:busroutePattern": "odpt.BusroutePattern:TokyuBus.Miya06.0004602726",
            "odpt:destinationBusstopPole": "odpt.BusstopPole:TokyuBus.Miyamaedairaeki.00240726."
          }
        ]
      },
      {
        "@id": "urn:ucode:_00001C00000000000001000003878000",
        "@type": "odpt:BusstopPoleTimetable",
        "dc:date": "2026-02-02T15:35:32+09:00",
        "@context": "http://vocab.odpt.org/context_odpt_BusstopPoleTimetable.jsonld",
        "dc:title": "宮０６.\n\t\t\t\t\t\t\t\t\t\t\n\t\t\t\t\t\t\t\t\t\t\n\t\t\t\t\t\t\t\t\t\t＜宮前区役所前経由＞ 宮前平駅ゆき\n\t\t\t\t\t\t\t\t\t\t宮前区役所前経由 宮前平駅ゆき\n\t\t\t\t\t\t\t\t\t:長坂:土曜",
        "odpt:note": "お問合せ先:東急バス 高津営業所",
        "owl:sameAs": "odpt.BusstopPoleTimetable:TokyuBus.Miya06.Nagasaka.00240741.b.0004602726.4.Saturday",
        "odpt:busroute": [
          "odpt.Busroute:TokyuBus.Miya06"
        ],
        "odpt:calendar": "odpt.Calendar:Saturday",
        "odpt:operator": "odpt.Operator:TokyuBus",
        "odpt:busstopPole": "odpt.BusstopPole:TokyuBus.Nagasaka.00240741.b",
        "odpt:busDirection": [
          "odpt.BusDirection:TokyuBus.Miyamaedairaeki"
        ],
        "odpt:busstopPoleTimetableObject": []
      },
      {
        "@id": "urn:ucode:_00001C00000000000001000003878001",
        "@type": "odpt:BusstopPoleTimetable",
        "dc:date": "2026-02-02T15:35:32+09:00",
        "@context": "http://vocab.odpt.org/context_odpt_BusstopPoleTimetable.jsonld",
        "dc:title": "宮０６.\n\t\t\t\t\t\t\t\t\t\t\n\t\t\t\t\t\t\t\t\t\t\n\t\t\t\t\t\t\t\t\t\t＜宮前区役所前経由＞ 宮前平駅ゆき\n\t\t\t\t\t\t\t\t\t\t宮前区役所前経由 宮前平駅ゆき\n\t\t\t\t\t\t\t\t\t:長坂:日曜",
        "odpt:note": "お問合せ先:東急バス 高津営業所",
        "owl:sameAs": "odpt.BusstopPoleTimetable:TokyuBus.Miya06.Nagasaka.00240741.b.0004602726.4.Sunday",
        "odpt:busroute": [
          "odpt.Busroute:TokyuBus.Miya06"
        ],
        "odpt:calendar": "odpt.Calendar:Sunday",
        "odpt:operator": "odpt.Operator:TokyuBus",
        "odpt:busstopPole": "odpt.BusstopPole:TokyuBus.Nagasaka.00240741.b",
        "odpt:busDirection": [
          "odpt.BusDirection:TokyuBus.Miyamaedairaeki"
        ],
        "odpt:busstopPoleTimetableObject": [
          {
            "odpt:isMidnight": false,
            "odpt:departureTime": "07:24",
            "odpt:busroutePattern": "odpt.BusroutePattern:TokyuBus.Miya06.0004602726",
            "odpt:destinationBusstopPole": "odpt.BusstopPole:TokyuBus.Miyamaedairaeki.00240726."
          },
          {
            "odpt:isMidnight": false,
            "odpt:departureTime": "08:13",
            "odpt:busroutePattern": "odpt.BusroutePattern:TokyuBus.Miya06.0004602726",
            "odpt:destinationBusstopPole": "odpt.BusstopPole:TokyuBus.Miyamaedairaeki.00240726."
          },
          {
            "odpt:isMidnight": false,
            "odpt:departureTime": "09:03",
            "odpt:busroutePattern": "odpt.BusroutePattern:TokyuBus.Miya06.0004602726",
            "odpt:destinationBusstopPole": "odpt.BusstopPole:TokyuBus.Miyamaedairaeki.00240726."
          },
          {
            "odpt:isMidnight": false,
            "odpt:departureTime": "09:53",
            "odpt:busroutePattern": "odpt.BusroutePattern:TokyuBus.Miya06.0004602726",
            "odpt:destinationBusstopPole": "odpt.BusstopPole:TokyuBus.Miyamaedairaeki.00240726."
          },
          {
            "odpt:isMidnight": false,
            "odpt:departureTime": "10:43",
            "odpt:busroutePattern": "odpt.BusroutePattern:TokyuBus.Miya06.0004602726",
            "odpt:destinationBusstopPole": "odpt.BusstopPole:TokyuBus.Miyamaedairaeki.00240726."
          },
          {
            "odpt:isMidnight": false,
            "odpt:departureTime": "11:33",
            "odpt:busroutePattern": "odpt.BusroutePattern:TokyuBus.Miya06.0004602726",
            "odpt:destinationBusstopPole": "odpt.BusstopPole:TokyuBus.Miyamaedairaeki.00240726."
          },
          {
            "odpt:isMidnight": false,
            "odpt:departureTime": "12:23",
            "odpt:busroutePattern": "odpt.BusroutePattern:TokyuBus.Miya06.0004602726",
            "odpt:destinationBusstopPole": "odpt.BusstopPole:TokyuBus.Miyamaedairaeki.00240726."
          },
          {
            "odpt:isMidnight": false,
            "odpt:departureTime": "13:13",
            "odpt:busroutePattern": "odpt.BusroutePattern:TokyuBus.Miya06.0004602726",
            "odpt:destinationBusstopPole": "odpt.BusstopPole:TokyuBus.Miyamaedairaeki.00240726."
          },
          {
            "odpt:isMidnight": false,
            "odpt:departureTime": "14:03",
            "odpt:busroutePattern": "odpt.BusroutePattern:TokyuBus.Miya06.0004602726",
            "odpt:destinationBusstopPole": "odpt.BusstopPole:TokyuBus.Miyamaedairaeki.00240726."
          },
          {
            "odpt:isMidnight": false,
            "odpt:departureTime": "14:53",
            "odpt:busroutePattern": "odpt.BusroutePattern:TokyuBus.Miya06.0004602726",
            "odpt:destinationBusstopPole": "odpt.BusstopPole:TokyuBus.Miyamaedairaeki.00240726."
          },
          {
            "odpt:isMidnight": false,
            "odpt:departureTime": "15:43",
            "odpt:busroutePattern": "odpt.BusroutePattern:TokyuBus.Miya06.0004602726",
            "odpt:destinationBusstopPole": "odpt.BusstopPole:TokyuBus.Miyamaedairaeki.00240726."
          },
          {
            "odpt:isMidnight": false,
            "odpt:departureTime": "16:33",
            "odpt:busroutePattern": "odpt.BusroutePattern:TokyuBus.Miya06.0004602726",
            "odpt:destinationBusstopPole": "odpt.BusstopPole:TokyuBus.Miyamaedairaeki.00240726."
          },
          {
            "odpt:isMidnight": false,
            "odpt:departureTime": "17:23",
            "odpt:busroutePattern": "odpt.BusroutePattern:TokyuBus.Miya06.0004602726",
            "odpt:destinationBusstopPole": "odpt.BusstopPole:TokyuBus.Miyamaedairaeki.00240726."
          },
          {
            "odpt:isMidnight": false,
            "odpt:departureTime": "18:13",
            "odpt:busroutePattern": "odpt.BusroutePattern:TokyuBus.Miya06.0004602726",
            "odpt:destinationBusstopPole": "odpt.BusstopPole:TokyuBus.Miyamaedairaeki.00240726."
          },
          {
            "odpt:isMidnight": false,
            "odpt:departureTime": "19:03",
            "odpt:busroutePattern": "odpt.BusroutePattern:TokyuBus.Miya06.0004602726",
            "odpt:destinationBusstopPole": "odpt.BusstopPole:TokyuBus.Miyamaedairaeki.00240726."
          }
        ]
      }
    ]
  }
}