{
  "createdAt": "2026-03-06T08:58:07.454Z",
  "expiresAt": "2026-03-06T09:58:07.454Z",
  "key": "{\"resource\":\"odpt:BusstopPoleTimetable\",\"query\":\"odpt:operator=odpt.Operator:TokyuBus&odpt:busstopPole=odpt.BusstopPole:TokyuBus.Hirakawa.00241300.a\",\"dump\":false}",
  "payload": {
    "meta": {
      "url": "https://api.odpt.org/api/v4/odpt:BusstopPoleTimetable?odpt:operator=odpt.Operator:TokyuBus&odpt:busstopPole=odpt.BusstopPole:TokyuBus.Hirakawa.00241300.a&acl:consumerKey=841qfdgzgywu5oktxrzqst5mosl5apeis3r5bz98aorxk8175pr1e7zd2k4pywqh",
      "count": 6,
      "maybeTruncated": false,
      "dump": false,
      "cacheHit": false,
      "cacheKey": "{\"resource\":\"odpt:BusstopPoleTimetable\",\"query\":\"odpt:operator=odpt.Operator:TokyuBus&odpt:busstopPole=odpt.BusstopPole:TokyuBus.Hirakawa.00241300.a\",\"dump\":false}"
    },
    "data": [
      {
        "@id": "urn:ucode:_00001C000000000000010000038772A6",
        "@type": "odpt:BusstopPoleTimetable",
        "dc:date": "2026-02-02T12:59:25+09:00",
        "@context": "http://vocab.odpt.org/context_odpt_BusstopPoleTimetable.jsonld",
        "dc:title": "た５１.\n\t\t\t\t\t\t\t\t\t\t\n\t\t\t\t\t\t\t\t\t\t\n\t\t\t\t\t\t\t\t\t\t たまプラーザ駅ゆき\n\t\t\t\t\t\t\t\t\t\t たまプラーザ駅ゆき\n\t\t\t\t\t\t\t\t\t:平川:平日",
        "odpt:note": "道路混雑等のため予定時刻通りに運行できないことがありますので、ご了承願います。お問合せ先:東急バス 虹が丘営業所",
        "owl:sameAs": "odpt.BusstopPoleTimetable:TokyuBus.Ta51.Hirakawa.00241300.a.0004600329.10.Weekday",
        "odpt:busroute": [
          "odpt.Busroute:TokyuBus.Ta51"
        ],
        "odpt:calendar": "odpt.Calendar:Weekday",
        "odpt:operator": "odpt.Operator:TokyuBus",
        "odpt:busstopPole": "odpt.BusstopPole:TokyuBus.Hirakawa.00241300.a",
        "odpt:busDirection": [
          "odpt.BusDirection:TokyuBus.Tamapura-zaeki"
        ],
        "odpt:busstopPoleTimetableObject": [
          {
            "odpt:isMidnight": false,
            "odpt:departureTime": "09:50",
            "odpt:busroutePattern": "odpt.BusroutePattern:TokyuBus.Ta51.0004600329",
            "odpt:destinationBusstopPole": "odpt.BusstopPole:TokyuBus.Tamapura-zaeki.00241216."
          },
          {
            "odpt:isMidnight": false,
            "odpt:departureTime": "11:05",
            "odpt:busroutePattern": "odpt.BusroutePattern:TokyuBus.Ta51.0004600329",
            "odpt:destinationBusstopPole": "odpt.BusstopPole:TokyuBus.Tamapura-zaeki.00241216."
          },
          {
            "odpt:isMidnight": false,
            "odpt:departureTime": "12:22",
            "odpt:busroutePattern": "odpt.BusroutePattern:TokyuBus.Ta51.0004600329",
            "odpt:destinationBusstopPole": "odpt.BusstopPole:TokyuBus.Tamapura-zaeki.00241216."
          },
          {
            "odpt:isMidnight": false,
            "odpt:departureTime": "13:21",
            "odpt:busroutePattern": "odpt.BusroutePattern:TokyuBus.Ta51.0004600329",
            "odpt:destinationBusstopPole": "odpt.BusstopPole:TokyuBus.Tamapura-zaeki.00241216."
          },
          {
            "odpt:isMidnight": false,
            "odpt:departureTime": "14:40",
            "odpt:busroutePattern": "odpt.BusroutePattern:TokyuBus.Ta51.0004600329",
            "odpt:destinationBusstopPole": "odpt.BusstopPole:TokyuBus.Tamapura-zaeki.00241216."
          },
          {
            "odpt:isMidnight": false,
            "odpt:departureTime": "15:55",
            "odpt:busroutePattern": "odpt.BusroutePattern:TokyuBus.Ta51.0004600329",
            "odpt:destinationBusstopPole": "odpt.BusstopPole:TokyuBus.Tamapura-zaeki.00241216."
          },
          {
            "odpt:isMidnight": false,
            "odpt:departureTime": "17:15",
            "odpt:busroutePattern": "odpt.BusroutePattern:TokyuBus.Ta51.0004600329",
            "odpt:destinationBusstopPole": "odpt.BusstopPole:TokyuBus.Tamapura-zaeki.00241216."
          }
        ]
      },
      {
        "@id": "urn:ucode:_00001C000000000000010000038772A7",
        "@type": "odpt:BusstopPoleTimetable",
        "dc:date": "2026-02-02T12:59:25+09:00",
        "@context": "http://vocab.odpt.org/context_odpt_BusstopPoleTimetable.jsonld",
        "dc:title": "た５１.\n\t\t\t\t\t\t\t\t\t\t\n\t\t\t\t\t\t\t\t\t\t\n\t\t\t\t\t\t\t\t\t\t たまプラーザ駅ゆき\n\t\t\t\t\t\t\t\t\t\t たまプラーザ駅ゆき\n\t\t\t\t\t\t\t\t\t:平川:土曜",
        "odpt:note": "道路混雑等のため予定時刻通りに運行できないことがありますので、ご了承願います。お問合せ先:東急バス 虹が丘営業所",
        "owl:sameAs": "odpt.BusstopPoleTimetable:TokyuBus.Ta51.Hirakawa.00241300.a.0004600329.10.Saturday",
        "odpt:busroute": [
          "odpt.Busroute:TokyuBus.Ta51"
        ],
        "odpt:calendar": "odpt.Calendar:Saturday",
        "odpt:operator": "odpt.Operator:TokyuBus",
        "odpt:busstopPole": "odpt.BusstopPole:TokyuBus.Hirakawa.00241300.a",
        "odpt:busDirection": [
          "odpt.BusDirection:TokyuBus.Tamapura-zaeki"
        ],
        "odpt:busstopPoleTimetableObject": []
      },
      {
        "@id": "urn:ucode:_00001C000000000000010000038772A8",
        "@type": "odpt:BusstopPoleTimetable",
        "dc:date": "2026-02-02T12:59:25+09:00",
        "@context": "http://vocab.odpt.org/context_odpt_BusstopPoleTimetable.jsonld",
        "dc:title": "た５１.\n\t\t\t\t\t\t\t\t\t\t\n\t\t\t\t\t\t\t\t\t\t\n\t\t\t\t\t\t\t\t\t\t たまプラーザ駅ゆき\n\t\t\t\t\t\t\t\t\t\t たまプラーザ駅ゆき\n\t\t\t\t\t\t\t\t\t:平川:日曜",
        "odpt:note": "道路混雑等のため予定時刻通りに運行できないことがありますので、ご了承願います。お問合せ先:東急バス 虹が丘営業所",
        "owl:sameAs": "odpt.BusstopPoleTimetable:TokyuBus.Ta51.Hirakawa.00241300.a.0004600329.10.Sunday",
        "odpt:busroute": [
          "odpt.Busroute:TokyuBus.Ta51"
        ],
        "odpt:calendar": "odpt.Calendar:Sunday",
        "odpt:operator": "odpt.Operator:TokyuBus",
        "odpt:busstopPole": "odpt.BusstopPole:TokyuBus.Hirakawa.00241300.a",
        "odpt:busDirection": [
          "odpt.BusDirection:TokyuBus.Tamapura-zaeki"
        ],
        "odpt:busstopPoleTimetableObject": [
          {
            "odpt:isMidnight": false,
            "odpt:departureTime": "09:50",
            "odpt:busroutePattern": "odpt.BusroutePattern:TokyuBus.Ta51.0004600329",
            "odpt:destinationBusstopPole": "odpt.BusstopPole:TokyuBus.Tamapura-zaeki.00241216."
          },
          {
            "odpt:isMidnight": false,
            "odpt:departureTime": "11:05",
            "odpt:busroutePattern": "odpt.BusroutePattern:TokyuBus.Ta51.0004600329",
            "odpt:destinationBusstopPole": "odpt.BusstopPole:TokyuBus.Tamapura-zaeki.00241216."
          },
          {
            "odpt:isMidnight": false,
            "odpt:departureTime": "12:22",
            "odpt:busroutePattern": "odpt.BusroutePattern:TokyuBus.Ta51.0004600329",
            "odpt:destinationBusstopPole": "odpt.BusstopPole:TokyuBus.Tamapura-zaeki.00241216."
          },
          {
            "odpt:isMidnight": false,
            "odpt:departureTime": "13:21",
            "odpt:busroutePattern": "odpt.BusroutePattern:TokyuBus.Ta51.0004600329",
            "odpt:destinationBusstopPole": "odpt.BusstopPole:TokyuBus.Tamapura-zaeki.00241216."
          },
          {
            "odpt:isMidnight": false,
            "odpt:departureTime": "14:40",
            "odpt:busroutePattern": "odpt.BusroutePattern:TokyuBus.Ta51.0004600329",
            "odpt:destinationBusstopPole": "odpt.BusstopPole:TokyuBus.Tamapura-zaeki.00241216."
          },
          {
            "odpt:isMidnight": false,
            "odpt:departureTime": "15:55",
            "odpt:busroutePattern": "odpt.BusroutePattern:TokyuBus.Ta51.0004600329",
            "odpt:destinationBusstopPole": "odpt.BusstopPole:TokyuBus.Tamapura-zaeki.00241216."
          },
          {
            "odpt:isMidnight": false,
            "odpt:departureTime": "17:15",
            "odpt:busroutePattern": "odpt.BusroutePattern:TokyuBus.Ta51.0004600329",
            "odpt:destinationBusstopPole": "odpt.BusstopPole:TokyuBus.Tamapura-zaeki.00241216."
          }
        ]
      },
      {
        "@id": "urn:ucode:_00001C000000000000010000038BC22A",
        "@type": "odpt:BusstopPoleTimetable",
        "dc:date": "2026-02-02T12:59:25+09:00",
        "@context": "http://vocab.odpt.org/context_odpt_BusstopPoleTimetable.jsonld",
        "dc:title": "た６４.\n\t\t\t\t\t\t\t\t\t\t\n\t\t\t\t\t\t\t\t\t\t\n\t\t\t\t\t\t\t\t\t\t＜寛永寺、美しが丘西一丁目経由＞ 虹が丘営業所ゆき\n\t\t\t\t\t\t\t\t\t\t寛永寺、美しが丘西一丁目経由 虹が丘営業所ゆき\n\t\t\t\t\t\t\t\t\t:平川:平日",
        "odpt:note": "お問合せ先:東急バス 虹が丘営業所",
        "owl:sameAs": "odpt.BusstopPoleTimetable:TokyuBus.Ta64.Hirakawa.00241300.a.0004603142.5.Weekday",
        "odpt:busroute": [
          "odpt.Busroute:TokyuBus.Ta64"
        ],
        "odpt:calendar": "odpt.Calendar:Weekday",
        "odpt:operator": "odpt.Operator:TokyuBus",
        "odpt:busstopPole": "odpt.BusstopPole:TokyuBus.Hirakawa.00241300.a",
        "odpt:busDirection": [
          "odpt.BusDirection:TokyuBus.Nijigaokaeigyousho"
        ],
        "odpt:busstopPoleTimetableObject": [
          {
            "odpt:isMidnight": false,
            "odpt:departureTime": "12:50",
            "odpt:busroutePattern": "odpt.BusroutePattern:TokyuBus.Ta64.0004603142",
            "odpt:destinationBusstopPole": "odpt.BusstopPole:TokyuBus.Nijigaokaeigyousho.00241232."
          }
        ]
      },
      {
        "@id": "urn:ucode:_00001C000000000000010000038BC22B",
        "@type": "odpt:BusstopPoleTimetable",
        "dc:date": "2026-02-02T12:59:25+09:00",
        "@context": "http://vocab.odpt.org/context_odpt_BusstopPoleTimetable.jsonld",
        "dc:title": "た６４.\n\t\t\t\t\t\t\t\t\t\t\n\t\t\t\t\t\t\t\t\t\t\n\t\t\t\t\t\t\t\t\t\t＜寛永寺、美しが丘西一丁目経由＞ 虹が丘営業所ゆき\n\t\t\t\t\t\t\t\t\t\t寛永寺、美しが丘西一丁目経由 虹が丘営業所ゆき\n\t\t\t\t\t\t\t\t\t:平川:土曜",
        "odpt:note": "お問合せ先:東急バス 虹が丘営業所",
        "owl:sameAs": "odpt.BusstopPoleTimetable:TokyuBus.Ta64.Hirakawa.00241300.a.0004603142.5.Saturday",
        "odpt:busroute": [
          "odpt.Busroute:TokyuBus.Ta64"
        ],
        "odpt:calendar": "odpt.Calendar:Saturday",
        "odpt:operator": "odpt.Operator:TokyuBus",
        "odpt:busstopPole": "odpt.BusstopPole:TokyuBus.Hirakawa.00241300.a",
        "odpt:busDirection": [
          "odpt.BusDirection:TokyuBus.Nijigaokaeigyousho"
        ],
        "odpt:busstopPoleTimetableObject": []
      },
      {
        "@id": "urn:ucode:_00001C000000000000010000038BC22C",
        "@type": "odpt:BusstopPoleTimetable",
        "dc:date": "2026-02-02T12:59:25+09:00",
        "@context": "http://vocab.odpt.org/context_odpt_BusstopPoleTimetable.jsonld",
        "dc:title": "た６４.\n\t\t\t\t\t\t\t\t\t\t\n\t\t\t\t\t\t\t\t\t\t\n\t\t\t\t\t\t\t\t\t\t＜寛永寺、美しが丘西一丁目経由＞ 虹が丘営業所ゆき\n\t\t\t\t\t\t\t\t\t\t寛永寺、美しが丘西一丁目経由 虹が丘営業所ゆき\n\t\t\t\t\t\t\t\t\t:平川:日曜",
        "odpt:note": "お問合せ先:東急バス 虹が丘営業所",
        "owl:sameAs": "odpt.BusstopPoleTimetable:TokyuBus.Ta64.Hirakawa.00241300.a.0004603142.5.Sunday",
        "odpt:busroute": [
          "odpt.Busroute:TokyuBus.Ta64"
        ],
        "odpt:calendar": "odpt.Calendar:Sunday",
        "odpt:operator": "odpt.Operator:TokyuBus",
        "odpt:busstopPole": "odpt.BusstopPole:TokyuBus.Hirakawa.00241300.a",
        "odpt:busDirection": [
          "odpt.BusDirection:TokyuBus.Nijigaokaeigyousho"
        ],
        "odpt:busstopPoleTimetableObject": []
      }
    ]
  }
}