[
  {
    "variant_id": "var_101_out_full",
    "route_id": "route_101",
    "direction": "outbound",
    "variant_name": "全区間往路",
    "start_terminal_id": "terminal_A",
    "end_terminal_id": "terminal_B",
    "segment_id_list": [
      "seg_out_01",
      "seg_out_02",
      "seg_out_03",
      "seg_out_04",
      "seg_out_05",
      "seg_out_06",
      "seg_out_07",
      "seg_out_08",
      "seg_out_09",
      "seg_out_10",
      "seg_out_11",
      "seg_out_12",
      "seg_out_13",
      "seg_out_14",
      "seg_out_15",
      "seg_out_16",
      "seg_out_17"
    ],
    "total_distance_km": 14.59,
    "total_runtime_min": 30.0,
    "is_primary": true,
    "notes": "全区間往路 (デポ → 終点)"
  },
  {
    "variant_id": "var_101_in_full",
    "route_id": "route_101",
    "direction": "inbound",
    "variant_name": "全区間復路",
    "start_terminal_id": "terminal_B",
    "end_terminal_id": "terminal_A",
    "segment_id_list": [
      "seg_inb_01",
      "seg_inb_02",
      "seg_inb_03",
      "seg_inb_04",
      "seg_inb_05",
      "seg_inb_06",
      "seg_inb_07",
      "seg_inb_08",
      "seg_inb_09",
      "seg_inb_10",
      "seg_inb_11",
      "seg_inb_12",
      "seg_inb_13",
      "seg_inb_14",
      "seg_inb_15",
      "seg_inb_16",
      "seg_inb_17"
    ],
    "total_distance_km": 14.59,
    "total_runtime_min": 30.0,
    "is_primary": true,
    "notes": "全区間復路 (終点 → デポ)"
  }
]
